{
  "tasks": [
    {
      "id": 1,
      "name": "Task One",
      "dueDate": "07/15/2019",
      "description": "Sample Descr",
      "completed": false,
      "priority": 1
    },
    {
      "id": 2,
      "name": "Task Two",
      "dueDate": "07/15/2019",
      "description": "asdsada",
      "completed": false,
      "priority": 2
    },
    {
      "id": 3,
      "name": "Task Three",
      "dueDate": "07/15/2019",
      "description": "",
      "completed": false,
      "priority": 3
    },
    {
      "id": 4,
      "name": "Task Four",
      "dueDate": "07/15/2019",
      "description": "12345",
      "completed": true,
      "priority": 5
    },
    {
      "id": 5,
      "name": "Task Five",
      "dueDate": "07/15/2019",
      "description": "test",
      "completed": false,
      "priority": 4
    },
    {
      "id": 6,
      "name": "Task Six",
      "dueDate": "07/15/2019",
      "description": "insert some sample description",
      "completed": true,
      "priority": 2
    },
    {
      "id": 7,
      "name": "Task Seven",
      "dueDate": "12/30/2016",
      "description": "zxcvb",
      "completed": false,
      "priority": 1
    },
    {
      "id": 8,
      "name": "Task Eight",
      "dueDate": "06/15/2019",
      "description": "asdfg",
      "completed": true,
      "priority": 2
    },
    {
      "id": 9,
      "name": "Task Nine",
      "dueDate": "07/21/2019",
      "description": "qwerty",
      "completed": true,
      "priority": 3
    },
    {
      "id": 10,
      "name": "Task Ten",
      "dueDate": "07/15/2019",
      "description": "",
      "completed": false,
      "priority": 5
    },
    {
      "id": 11,
      "name": "Task Eleven",
      "dueDate": "07/15/2019",
      "description": "asahdjaksdasd",
      "completed": true,
      "priority": 4
    },
    {
      "id": 12,
      "name": "Task Twelve",
      "dueDate": "07/15/2019",
      "description": "sakdlasjdlkasjdlka",
      "completed": false,
      "priority": 5
    }
  ]
}
